{
  "ID": "1bb3194f-fc8e-4669-912b-e8c9fa93830e",
  "Version": "2.3.4",
  "Name": "soldier_lvl2",
  "Content": {
    "Content": {
      "Animation": {
        "Duration": 65,
        "Speed": 1.0,
        "ActivedAnimationName": "dead",
        "Timelines": [
          {
            "ActionTag": 1062457691,
            "Property": "FileData",
            "Frames": [
              {
                "TextureFile": {
                  "Type": "PlistSubImage",
                  "Path": "soldier_lvl2_0001.png",
                  "Plist": "soldier_lvl2.plist"
                },
                "FrameIndex": 0,
                "Tween": false,
                "ctype": "TextureFrameData"
              },
              {
                "TextureFile": {
                  "Type": "PlistSubImage",
                  "Path": "soldier_lvl2_0002.png",
                  "Plist": "soldier_lvl2.plist"
                },
                "FrameIndex": 5,
                "Tween": false,
                "ctype": "TextureFrameData"
              },
              {
                "TextureFile": {
                  "Type": "PlistSubImage",
                  "Path": "soldier_lvl2_0003.png",
                  "Plist": "soldier_lvl2.plist"
                },
                "FrameIndex": 10,
                "Tween": false,
                "ctype": "TextureFrameData"
              },
              {
                "TextureFile": {
                  "Type": "PlistSubImage",
                  "Path": "soldier_lvl2_0004.png",
                  "Plist": "soldier_lvl2.plist"
                },
                "FrameIndex": 15,
                "Tween": false,
                "ctype": "TextureFrameData"
              },
              {
                "TextureFile": {
                  "Type": "PlistSubImage",
                  "Path": "soldier_lvl2_0005.png",
                  "Plist": "soldier_lvl2.plist"
                },
                "FrameIndex": 20,
                "Tween": false,
                "ctype": "TextureFrameData"
              },
              {
                "TextureFile": {
                  "Type": "PlistSubImage",
                  "Path": "soldier_lvl2_0006.png",
                  "Plist": "soldier_lvl2.plist"
                },
                "FrameIndex": 25,
                "Tween": false,
                "ctype": "TextureFrameData"
              },
              {
                "TextureFile": {
                  "Type": "PlistSubImage",
                  "Path": "soldier_lvl2_0007.png",
                  "Plist": "soldier_lvl2.plist"
                },
                "FrameIndex": 30,
                "Tween": false,
                "ctype": "TextureFrameData"
              },
              {
                "TextureFile": {
                  "Type": "PlistSubImage",
                  "Path": "soldier_lvl2_0011.png",
                  "Plist": "soldier_lvl2.plist"
                },
                "FrameIndex": 35,
                "Tween": false,
                "ctype": "TextureFrameData"
              },
              {
                "TextureFile": {
                  "Type": "PlistSubImage",
                  "Path": "soldier_lvl2_0014.png",
                  "Plist": "soldier_lvl2.plist"
                },
                "FrameIndex": 40,
                "Tween": false,
                "ctype": "TextureFrameData"
              },
              {
                "TextureFile": {
                  "Type": "PlistSubImage",
                  "Path": "soldier_lvl2_0018.png",
                  "Plist": "soldier_lvl2.plist"
                },
                "FrameIndex": 45,
                "Tween": false,
                "ctype": "TextureFrameData"
              },
              {
                "TextureFile": {
                  "Type": "PlistSubImage",
                  "Path": "soldier_lvl2_0019.png",
                  "Plist": "soldier_lvl2.plist"
                },
                "FrameIndex": 50,
                "Tween": false,
                "ctype": "TextureFrameData"
              },
              {
                "TextureFile": {
                  "Type": "PlistSubImage",
                  "Path": "soldier_lvl2_0020.png",
                  "Plist": "soldier_lvl2.plist"
                },
                "FrameIndex": 55,
                "Tween": false,
                "ctype": "TextureFrameData"
              },
              {
                "TextureFile": {
                  "Type": "PlistSubImage",
                  "Path": "soldier_lvl2_0021.png",
                  "Plist": "soldier_lvl2.plist"
                },
                "FrameIndex": 60,
                "Tween": false,
                "ctype": "TextureFrameData"
              },
              {
                "TextureFile": {
                  "Type": "PlistSubImage",
                  "Path": "soldier_lvl2_0022.png",
                  "Plist": "soldier_lvl2.plist"
                },
                "FrameIndex": 65,
                "Tween": false,
                "ctype": "TextureFrameData"
              }
            ],
            "ctype": "TimelineData"
          }
        ],
        "ctype": "TimelineActionData"
      },
      "AnimationList": [
        {
          "StartIndex": 0,
          "EndIndex": 4,
          "Name": "idle",
          "ctype": "AnimationInfoData"
        },
        {
          "StartIndex": 5,
          "EndIndex": 29,
          "Name": "run",
          "ctype": "AnimationInfoData"
        },
        {
          "StartIndex": 30,
          "EndIndex": 44,
          "Name": "attack",
          "ctype": "AnimationInfoData"
        },
        {
          "StartIndex": 45,
          "EndIndex": 65,
          "Name": "dead",
          "ctype": "AnimationInfoData"
        }
      ],
      "ObjectData": {
        "Tag": 7,
        "Children": [
          {
            "FileData": {
              "Type": "PlistSubImage",
              "Path": "soldier_lvl2_0006.png",
              "Plist": "soldier_lvl2.plist"
            },
            "BlendFunc": {
              "Src": 1,
              "Dst": 771
            },
            "AnchorPoint": {
              "ScaleX": 0.5,
              "ScaleY": 0.5
            },
            "Position": {
              "X": 0.0,
              "Y": 23.0
            },
            "Scale": {
              "ScaleX": 1.0,
              "ScaleY": 1.0
            },
            "CColor": {},
            "IconVisible": false,
            "PrePosition": {
              "X": 0.0,
              "Y": 0.0
            },
            "PreSize": {
              "X": 0.0,
              "Y": 0.0
            },
            "LeftMargin": -56.0,
            "RightMargin": -56.0,
            "TopMargin": -55.0,
            "BottomMargin": -9.0,
            "Tag": 8,
            "ActionTag": 1062457691,
            "Size": {
              "X": 112.0,
              "Y": 64.0
            },
            "Name": "soldier_lvl2",
            "ctype": "SpriteObjectData"
          }
        ],
        "Size": {
          "X": 0.0,
          "Y": 0.0
        },
        "Name": "Node",
        "ctype": "SingleNodeObjectData"
      },
      "UsedResources": [
        "soldier_lvl2.plist",
        "soldier_lvl2.png"
      ],
      "ctype": "GameFileData"
    }
  },
  "Type": "Node"
}